postman_cli_transformer/__init__.py
postman_cli_transformer/__main__.py
postman_cli_transformer/cli.py
postman_cli_transformer/decipherer.py
postman_cli_transformer/junit_transformer.py
postman_cli_transformer/parsers.py
postman_cli_transformer/processor.py
postman_cli_transformer/unicode_constants.py
postman_cli_transformer-0.4.2.dist-info/LICENSE
postman_cli_transformer-0.4.2.dist-info/METADATA
postman_cli_transformer-0.4.2.dist-info/WHEEL
postman_cli_transformer-0.4.2.dist-info/entry_points.txt
postman_cli_transformer-0.4.2.dist-info/top_level.txt
postman_cli_transformer-0.4.2.dist-info/RECORD
