Metadata-Version: 2.1
Name: postman-cli-transformer
Version: 0.4.2
Summary: This package will take as input the STDOUT from a Postman CLI collection run and transform the output text to a JSON doc which may in turn be transformed.
Author: Craig Erdmann
License: Apache-2.0
Project-URL: Homepage, https://github.com/cerdmann/postman-cli-transformer
Project-URL: Changelog, https://github.com/cerdmann/postman-cli-transformer/releases
Project-URL: Issues, https://github.com/cerdmann/postman-cli-transformer/issues
Project-URL: CI, https://github.com/cerdmann/postman-cli-transformer/actions
Classifier: License :: OSI Approved :: Apache Software License
Requires-Python: >=3.10
License-File: LICENSE
Requires-Dist: click
Provides-Extra: test
Requires-Dist: pytest ; extra == 'test'
